boost_hist_plot.py
boost_hist_plot-0.1.dist-info/LICENSE
boost_hist_plot-0.1.dist-info/WHEEL
boost_hist_plot-0.1.dist-info/METADATA
boost_hist_plot-0.1.dist-info/RECORD
