Metadata-Version: 2.1
Name: boost_hist_plot
Version: 0.1
Summary: Functions to plot boost histograms.
Author-email: Cyrille Praz <code.cyrraz@protonmail.com>
Classifier: License :: OSI Approved :: GNU General Public License v3 or later (GPLv3+)
Project-URL: Home, https://github.com/cyrraz/boost_hist_plot
